dezrest/__init__.py
dezrest/__main__.py
dezrest/dezrest.py
dezrest/sanic__main__has-problem-with-ezbee.py-
dezrest-0.1.0.dist-info/entry_points.txt
dezrest-0.1.0.dist-info/LICENSE
dezrest-0.1.0.dist-info/WHEEL
dezrest-0.1.0.dist-info/METADATA
dezrest-0.1.0.dist-info/RECORD
