Metadata-Version: 2.1
Name: dezrest
Version: 0.1.0
Summary: serve ez/dz/de bee via FastAPI rest
Home-page: https://github.com/ffreemt/dezbee-rest
License: MIT
Author: ffreemt
Requires-Python: >=3.8.3,<4.0.0
Classifier: License :: OSI Approved :: MIT License
Classifier: Programming Language :: Python :: 3
Classifier: Programming Language :: Python :: 3.9
Classifier: Programming Language :: Python :: 3.10
Requires-Dist: ezbee (>=0.1.3,<0.2.0)
Requires-Dist: fastapi (>=0.88.0,<0.89.0)
Requires-Dist: logzero (>=1.7.0,<2.0.0)
Requires-Dist: pybind11 (>=2.10.1,<3.0.0)
Requires-Dist: set-loglevel (>=0.1.2,<0.2.0)
Requires-Dist: uvicorn[standard] (>=0.20.0,<0.21.0)
Project-URL: Repository, https://github.com/ffreemt/dezbee-rest
